{
    "AX": {
        "error": 0.004638557934111819, 
        "filter_outliers_dict": {
            "filter_outliers": true, 
            "iterations": 1, 
            "std_devs": 2
        }, 
        "fit": "average", 
        "value": 0.04357119264503422
    }, 
    "CDD": {
        "error": 4.27719000478983e-06, 
        "filter_outliers_dict": {
            "filter_outliers": true, 
            "iterations": 1, 
            "std_devs": 10
        }, 
        "fit": "average", 
        "value": 1.626341751151249e-05
    }, 
    "H1": {
        "error": 0.0028337217196267046, 
        "filter_outliers_dict": {
            "filter_outliers": true, 
            "iterations": 1, 
            "std_devs": 2
        }, 
        "fit": "average", 
        "value": -0.034725545200575574
    }, 
    "H2": {
        "error": 0.0035644726452385106, 
        "filter_outliers_dict": {
            "filter_outliers": true, 
            "iterations": 1, 
            "std_devs": 2
        }, 
        "fit": "average", 
        "value": 0.06360467441880199
    }, 
    "L1": {
        "error": 0.0017280069277170738, 
        "filter_outliers_dict": {
            "filter_outliers": true, 
            "iterations": 1, 
            "std_devs": 2
        }, 
        "fit": "average", 
        "value": -0.00010109924698851048
    }, 
    "L2": {
        "error": 0.004589977613035141, 
        "filter_outliers_dict": {
            "filter_outliers": true, 
            "iterations": 1, 
            "std_devs": 2
        }, 
        "fit": "average", 
        "value": 0.13585888661773496
    }
}